sjgeminifvai/__init__.py
sjgeminifvai/jclass/__init__.py
sjgeminifvai/jclass/blokthreshold.py
sjgeminifvai/jclass/contentbuilder.py
sjgeminifvai/jclass/fvai.py
sjgeminifvai/jclass/gcbuilder.py
sjgeminifvai/jclass/gcr.py
sjgeminifvai/jclass/gmf.py
sjgeminifvai/jclass/harmcategory.py
sjgeminifvai/jclass/optionals.py
sjgeminifvai/jclass/safetysettings.py
sjgeminifvai/jinterface/__init__.py
sjgeminifvai-0.1.0.dist-info/METADATA
sjgeminifvai-0.1.0.dist-info/WHEEL
sjgeminifvai-0.1.0.dist-info/RECORD
