Metadata-Version: 2.1
Name: sjgeminifvai
Version: 0.1.0
Summary: Access Gemini Android SDK in Python
Author: Kenechukwu Akubue
Author-email: kengoon19@gmail.com
Requires-Python: >=3.8,<4.0
Classifier: Programming Language :: Python :: 3
Classifier: Programming Language :: Python :: 3.8
Classifier: Programming Language :: Python :: 3.9
Classifier: Programming Language :: Python :: 3.10
Classifier: Programming Language :: Python :: 3.11
Classifier: Programming Language :: Python :: 3.12
Requires-Dist: pyjnius (>=1.6.1,<2.0.0)
Requires-Dist: simplejnius (>=0.1.3,<0.2.0)
